LpImagesDownloader/__init__.py
LpImagesDownloader/lid.py
LpImagesDownloader-1.1.0.dist-info/METADATA
LpImagesDownloader-1.1.0.dist-info/WHEEL
LpImagesDownloader-1.1.0.dist-info/entry_points.txt
LpImagesDownloader-1.1.0.dist-info/top_level.txt
LpImagesDownloader-1.1.0.dist-info/RECORD
