Metadata-Version: 2.1
Name: LpImagesDownloader
Version: 1.1.0
Summary: A powerful Python package to automate image downloading from any webpage with robust error handling and detailed logging.
Home-page: https://github.com/LpCodes/LP-All-Images-Downloader
Author: Lpcodes
Author-email: lovelesh_p@zohomail.in
Classifier: Development Status :: 5 - Production/Stable
Classifier: Programming Language :: Python :: 3
Classifier: Programming Language :: Python :: 3.7
Classifier: Programming Language :: Python :: 3.8
Classifier: Programming Language :: Python :: 3.9
Classifier: Programming Language :: Python :: 3.10
Classifier: Programming Language :: Python :: 3.11
Classifier: License :: OSI Approved :: MIT License
Classifier: Operating System :: OS Independent
Requires-Python: >=3.7
Requires-Dist: requests <3.0.0,>=2.28.2
Requires-Dist: selenium <5.0.0,>=4.8.2
Requires-Dist: validators <0.21.0,>=0.20.0
Requires-Dist: webdriver-manager <4.0.0,>=3.8.5
